{
  "metadata": {
    "splash": {
      "title": "Inicio",
      "content": "Bienvenidos a la primera antología de la red de Literatura Electrónica Latinoamericana."
    },
    "obras": {
      "title": "Obras",
      "content": "Listado de obras de la antología."
    },
    "obra": {
      "title": "Obra",
      "content": "Descripción de la obra"
    },
    "acerca": {
      "title": "Acerca de",
      "content": "Mensaje del comité editorial"
    },
    "autores": {
      "title": "Autores",
      "content": "Listado de autores de la antología"
    },
    "autor": {
      "title": "Autor",
      "content": "Biografía del autor"
    },
    "fecha": {
      "title": "Años",
      "content": "Listado de obras por año"
    },
    "paises": {
      "title": "Países",
      "content": "Listado de obras por país"
    },
    "categorias": {
      "title": "Categorías",
      "content": "Listado de obras por categoría"
    },
    "tecnologias": {
      "title": "Tecnologías",
      "content": "Listado de obras por tecnología"
    }
  }
}
